driver_sble_py_klsblelcf/__about__.py
driver_sble_py_klsblelcf/__init__.py
driver_sble_py_klsblelcf/_helpers.py
driver_sble_py_klsblelcf/power.py
driver_sble_py_klsblelcf/protocols/__init__.py
driver_sble_py_klsblelcf/protocols/data_unit/__init__.py
driver_sble_py_klsblelcf/protocols/data_unit/data_unit.py
driver_sble_py_klsblelcf/protocols/host/__init__.py
driver_sble_py_klsblelcf/protocols/host/host_handler.py
driver_sble_py_klsblelcf/transports/__init__.py
driver_sble_py_klsblelcf/transports/serial.py
driver_sble_py_klsblelcf-1.1.1.dist-info/METADATA
driver_sble_py_klsblelcf-1.1.1.dist-info/WHEEL
driver_sble_py_klsblelcf-1.1.1.dist-info/licenses/LICENSE.txt
driver_sble_py_klsblelcf-1.1.1.dist-info/RECORD
