Metadata-Version: 2.4
Name: driver-sble-py-klsblelcf
Version: 1.1.1
Project-URL: Documentation, https://github.com/unknown/driver-sble-py-klsblelcf#readme
Project-URL: Issues, https://github.com/unknown/driver-sble-py-klsblelcf/issues
Project-URL: Source, https://github.com/unknown/driver-sble-py-klsblelcf
Author-email: Ibon Zalbide <ibon.zalbie@kliskatek.com>
License-Expression: MIT
License-File: LICENSE.txt
Classifier: Development Status :: 4 - Beta
Classifier: Programming Language :: Python
Classifier: Programming Language :: Python :: 3.8
Classifier: Programming Language :: Python :: 3.9
Classifier: Programming Language :: Python :: 3.10
Classifier: Programming Language :: Python :: 3.11
Classifier: Programming Language :: Python :: 3.12
Classifier: Programming Language :: Python :: Implementation :: CPython
Classifier: Programming Language :: Python :: Implementation :: PyPy
Requires-Python: >=3.8
Requires-Dist: crccheck
Requires-Dist: pyserial
